{
  "artists": [
    {
      "word": "B",
      "image": "./imgs/bloo.png",
      "name": "BLOO",
      "korName": "(블루)",
      "comment": "bloo=하나의 장르 느낌, 최애 랩퍼 1순위",
      "albums": [
        "2016.06.18 Tony",
        "2017.02.23 Better",
        "2017.06.24 Hennessy",
        "2017.12.06 Downtown Baby EP",
        "2018.04.30 Drink Slow Henny",
        "2018.06.18 싸가지 (So Rude)",
        "2018.11.19 BLOO IN WONDERLAND EP",
        "2019.09.25 It's not Love I'm just Drunk EP",
        "2020.07.23 Hey, go smile",
        "2020.09.10 내 탓",
        "2021.02.04 DRAMA",
        "2021.03.25 Bloo Story",
        "2021.06.17 BLOO IN WONDERLAND 2"
      ]
    },
    {
      "word": "C",
      "image": "./imgs/camo.png",
      "name": "CAMO",
      "korName": "(카모)",
      "comment": "핫 루키, 외힙같은 사운드",
      "albums": [
        "2020.03.10 ICE",
        "2020.09.02 Life is wet",
        "2021.05.21 Fragile"
      ]
    },
    {
      "word": "B",
      "image": "./imgs/beenzino.png",
      "name": "Beenzino",
      "korName": "(빈지노)",
      "comment": "래퍼들의 래퍼, IAB STUDIO",
      "albums": [
        "2012.07.03 24:26",
        "2013.12.18 Dali, Van, Picasso",
        "2014.07.16 Up All Night",
        "2015.03.11 어쩌라고 (so what)",
        "2015.10.09 Break",
        "2015.11.30 We Are Going To",
        "2016.05.31 12",
        "2019.04.23 OKGO",
        "2019.07.21 Fashion Hoarder",
        "2019.10.19 Blurry"
      ]
    },
    {
      "word": "P",
      "image": "./imgs/pop smoke.png",
      "name": "Pop Smoke",
      "korName": "(팝 스모크)",
      "comment": "드릴 붐의 장본인, RIP",
      "albums": [
        "2019.07.26 Meet The Woo",
        "2020.02.07 Meet The Woo 2",
        "2020.07.03 Shoot For The Stars, Aim For The Moon",
        "2020.09.22 Mood Swings",
        "2020.09.30 Enjoy Yourself",
        "2020.10.07 For The Night",
        "2021.07.15 Faith"
      ]
    },
    {
      "word": "I",
      "image": "./imgs/iu.png",
      "name": "IU",
      "korName": "(아이유)",
      "comment": "국힙 원탑 아이유!",
      "albums": [
        "2008.09.20 Lost And Found",
        "2009.04.23 Growing Up",
        "2009.10.27 IU...IM",
        "2010.12.09 Real",
        "2011.02.17 Real+",
        "2011.11.29 Last Fantasy",
        "2012.05.11 스무 살의 봄",
        "2013.10.10 Modern Times",
        "2013.12.20 Modern Times Epilogue",
        "2014.05.15 꽃갈피",
        "2015.10.23 CHAT-SHIRE",
        "2017.04.21 Palette",
        "2017.09.22 꽃갈피 둘",
        "2019.11.18 Love poem",
        "2021.03.25 LILAC"
      ]
    },
    {
      "word": "M",
      "image": "./imgs/migos.png",
      "name": "Migos",
      "korName": "(미고스)",
      "comment": "트랩 킹, 미국의 리듬파워 (?)",
      "albums": [
        "2015.07.31 Yung Rich Nation",
        "2017.01.27 Culture",
        "2018.01.26 Culture II",
        "2021.06.11 Culture III"
      ]
    },
    {
      "word": "A",
      "image": "./imgs/Ash island.png",
      "name": "ASH ISLAND",
      "korName": "(애쉬 아일랜드)",
      "comment": "국힙 EMO 힙합의 미래",
      "albums": [
        "2018.11.21 DEADSTAR",
        "2019.03.22 ASH",
        "2019.04.08 More ASH",
        "2021.03.05 ISLAND",
        "2021.05.05 More ISLAND"
      ]
    },
    {
      "word": "J",
      "image": "./imgs/jvcki wai.png",
      "name": "Jvcki Wai",
      "korName": "(재키 와이)",
      "comment": "국힙 원탑 여성 래퍼, 가사 수준이 높다",
      "albums": [
        "2016.11.02 EXPOSURE",
        "2017.12.20 Neo EvE",
        "2018.07.06 Enchanted Propaganda"
      ]
    },
    {
      "word": "K",
      "image": "./imgs/keith ape.png",
      "name": "Keith Ape",
      "korName": "(키스 에이프)",
      "comment": "나한텐 이 형이 외힙이였다...",
      "albums": [
        "2014.10.14 Psycho'14",
        "2015.01.01 It G Ma (Feat. Okasian, JayAllDay, Loota, Kohh)",
        "2018.10.12 Born Again",
        "2019.07.03 Love Song (Feat. A14 & Lil Darkie)",
        "2019.07.16 No Cap (Feat. Lil Darkie)",
        "2019.09.15 PUMPED UP KEITH !",
        "2019.12.09 DIE AND RESPAWN (DOWNBAD REMIX) with Okasian, PNSB)",
        "2020.09.13 KILL THAT DUBBA LIKE BUBBA! (feat. KILLTJ)",
        "2020.11.05 VAMP FRIDAY (Friday Remix) (feat. Christ Dillinger)",
        "2021.04.01 LET'S PLAY! YOU! MAKE ME SAD!!!",
        "2021.05.24 Yuh Dig"
      ]
    },
    {
      "word": "O",
      "image": "./imgs/okasian.png",
      "name": "Okasian",
      "korName": "(오케이션)",
      "comment": "새 앨범이 빠를까 남북통일이 빠를까",
      "albums": ["2012.12.06 탑승수속"]
    },
    {
      "word": "S",
      "image": "./imgs/sun-young.png",
      "name": "Seon Young",
      "korName": "(선영이 사랑해용)",
      "comment": "나는 선영이를 평생 사랑합니다",
      "albums": ["2021.01.23 순용❤선영"]
    },
    {
      "word": "T",
      "image": "./imgs/the quiett.png",
      "name": "The Quiett",
      "korName": "(더 콰이엇)",
      "comment": "국힙 리빙 레전드, 게이되는 랩",
      "albums": [
        "2005.07.28 Music",
        "2006.02.03 Q Train",
        "2007.12.18 The Real Me",
        "2010.03.11 Quiet Storm : A Night Record",
        "2013.02.22 AMBITIQN",
        "2015.10.15 1 Life 2 Live",
        "2016.04.29 Q Train 2",
        "2017.05.18 Millionaire Poetry",
        "2018.09.07 glow forever"
      ]
    }
  ]
}
